[{"id":1,"nome":"Ação Civil Pública"},{"id":2,"nome":"Agenda"},{"id":3,"nome":"Análise"},{"id":4,"nome":"Anexo"},{"id":5,"nome":"Apresentação"},{"id":6,"nome":"Arquivo"},{"id":7,"nome":"Ata"},{"id":8,"nome":"Caderno "},{"id":9,"nome":"Quadro de contribuições"},{"id":10,"nome":"Contrato"},{"id":11,"nome":"Contribuições"},{"id":12,"nome":"Convocação"},{"id":13,"nome":"Cronograma"},{"id":14,"nome":"Decreto"},{"id":15,"nome":"Deferimento"},{"id":16,"nome":"Despacho"},{"id":17,"nome":"Despacho Autorizatório SMDU-Gabinete"},{"id":18,"nome":"Devolutiva"},{"id":19,"nome":"Diagnóstico"},{"id":20,"nome":"Diretrizes"},{"id":21,"nome":"Divulgação"},{"id":22,"nome":"Edital"},{"id":23,"nome":"EIA RIMA"},{"id":24,"nome":"Especificações Técnicas"},{"id":25,"nome":"Estudos"},{"id":26,"nome":"Exposição de motivos"},{"id":27,"nome":"Extrato de reunião"},{"id":28,"nome":"Informe"},{"id":29,"nome":"KML"},{"id":30,"nome":"Lei"},{"id":31,"nome":"Licença Ambiental Prévia (LAP)"},{"id":32,"nome":"Lista de Presença"},{"id":33,"nome":"Diagnóstico e Programa de Interesse Público"},{"id":34,"nome":"Mapa"},{"id":35,"nome":"Mapas"},{"id":36,"nome":"Minuta"},{"id":37,"nome":"Minuta de Decreto"},{"id":38,"nome":"Minuta do Projeto de Lei"},{"id":39,"nome":"Modelagem Econômica da Intervenção"},{"id":40,"nome":"Modelo de Gestão"},{"id":41,"nome":"Modelo Jurídico"},{"id":42,"nome":"Nota Técnica"},{"id":43,"nome":"Notícia"},{"id":44,"nome":"Ofício"},{"id":45,"nome":"Página"},{"id":46,"nome":"Parecer"},{"id":47,"nome":"Pedido"},{"id":48,"nome":"Plano"},{"id":49,"nome":"Portaria"},{"id":50,"nome":"Processo Administrativo"},{"id":51,"nome":"Processo SEI"},{"id":52,"nome":"Programa de Interesse Público"},{"id":53,"nome":"Projeto de Lei"},{"id":54,"nome":"Pronunciamento"},{"id":55,"nome":"Proposta de Ordenamento Urbanístico"},{"id":56,"nome":"Publicação de Autorização para elaboração do PIU"},{"id":57,"nome":"Quadro"},{"id":58,"nome":"Quadros "},{"id":59,"nome":"Registro"},{"id":60,"nome":"Relatório"},{"id":61,"nome":"Republicação"},{"id":62,"nome":"Sistematização"},{"id":63,"nome":"Suspensão"},{"id":64,"nome":"Termo de reunião"},{"id":65,"nome":"Texto"},{"id":66,"nome":"Vídeo"},{"id":67,"nome":"Memorando"},{"id":68,"nome":"Resolução"},{"id":69,"nome":"Elementos necessários à elaboração do PIU"},{"id":70,"nome":"Manifestação de Interesse Privado"},{"id":71,"nome":"Convite"},{"id":72,"nome":"Planta"},{"id":73,"nome":"Plantas"},{"id":74,"nome":"Protocolo"}]